easyformula/__init__.py
easyformula/formulas.py
easyformula-0.1.dist-info/licenses/LICENSE
easyformula-0.1.dist-info/METADATA
easyformula-0.1.dist-info/WHEEL
easyformula-0.1.dist-info/top_level.txt
easyformula-0.1.dist-info/RECORD
